ecotricity/__init__.py
ecotricity/client/__init__.py
ecotricity/client/dto/Account.py
ecotricity/client/dto/AccountsData.py
ecotricity/client/dto/AccountsResult.py
ecotricity/client/dto/Agreement.py
ecotricity/client/dto/AgreementsData.py
ecotricity/client/dto/AgreementsResult.py
ecotricity/client/dto/BillingAddress.py
ecotricity/client/dto/MeterPoint.py
ecotricity/client/dto/MeterRead.py
ecotricity/client/dto/MeterReadsData.py
ecotricity/client/dto/MeterReadsResult.py
ecotricity/client/dto/Product.py
ecotricity/client/dto/Session.py
ecotricity/client/dto/TokensData.py
ecotricity/client/dto/TokensResult.py
ecotricity/client/dto/__init__.py
ecotricity/client/exceptions/ApiException.py
ecotricity/client/exceptions/EcotricityClientException.py
ecotricity/client/exceptions/ResponseDecodeException.py
ecotricity/client/exceptions/__init__.py
ecotricity/client/requests/AccountsRequest.py
ecotricity/client/requests/AgreementsRequest.py
ecotricity/client/requests/BaseRequest.py
ecotricity/client/requests/ReadsRequest.py
ecotricity/client/requests/TokensRequest.py
ecotricity/client/requests/__init__.py
ecotricity/client/service/__init__.py
ecotricity/client/service/session.py
ecotricity_client-1.0.1.dist-info/LICENCE
ecotricity_client-1.0.1.dist-info/METADATA
ecotricity_client-1.0.1.dist-info/WHEEL
ecotricity_client-1.0.1.dist-info/top_level.txt
ecotricity_client-1.0.1.dist-info/RECORD
