Metadata-Version: 2.1
Name: ecotricity-client
Version: 1.0.1
Summary: Wrapper around the Ecotricity API
Home-page: https://github.com/dezzak/ecotricity-client
Author: Derek Kaye
Project-URL: Homepage, https://github.com/dezzak/ecotricity-client
Project-URL: Bug Tracker, https://github.com/dezzak/ecotricity-client/issues
Classifier: Programming Language :: Python :: 3.9
Classifier: Programming Language :: Python :: 3.10
Classifier: License :: OSI Approved :: Apache Software License
Classifier: Topic :: Software Development :: Libraries
Requires-Python: >=3.9
License-File: LICENCE
Requires-Dist: dataclass-wizard (>=0.22.2)
Requires-Dist: requests (>=2.28.2)
Requires-Dist: PyJWT (>=2.5.0)
